odoo8_addon_l10n_it_base-8.0.0.1.0.99.dev11-py3.8-nspkg.pth
odoo_addons/l10n_it_base/AUTHORS.txt
odoo_addons/l10n_it_base/__init__.py
odoo_addons/l10n_it_base/__openerp__.py
odoo_addons/l10n_it_base/i18n/es.po
odoo_addons/l10n_it_base/i18n/it.po
odoo_addons/l10n_it_base/i18n/l10n_it_base.pot
odoo_addons/l10n_it_base/i18n/sl.po
odoo_addons/l10n_it_base/model/__init__.py
odoo_addons/l10n_it_base/model/res_config.py
odoo_addons/l10n_it_base/static/description/icon.png
odoo_addons/l10n_it_base/view/res_config_view.xml
odoo8_addon_l10n_it_base-8.0.0.1.0.99.dev11.dist-info/METADATA
odoo8_addon_l10n_it_base-8.0.0.1.0.99.dev11.dist-info/WHEEL
odoo8_addon_l10n_it_base-8.0.0.1.0.99.dev11.dist-info/namespace_packages.txt
odoo8_addon_l10n_it_base-8.0.0.1.0.99.dev11.dist-info/top_level.txt
odoo8_addon_l10n_it_base-8.0.0.1.0.99.dev11.dist-info/RECORD
